odoo/addons/base_tier_validation_formula/README.rst
odoo/addons/base_tier_validation_formula/__init__.py
odoo/addons/base_tier_validation_formula/__manifest__.py
odoo/addons/base_tier_validation_formula/i18n/base_tier_validation_formula.pot
odoo/addons/base_tier_validation_formula/i18n/es.po
odoo/addons/base_tier_validation_formula/i18n/zh_CN.po
odoo/addons/base_tier_validation_formula/models/__init__.py
odoo/addons/base_tier_validation_formula/models/tier_definition.py
odoo/addons/base_tier_validation_formula/models/tier_review.py
odoo/addons/base_tier_validation_formula/models/tier_validation.py
odoo/addons/base_tier_validation_formula/readme/CONTRIBUTORS.rst
odoo/addons/base_tier_validation_formula/readme/DESCRIPTION.rst
odoo/addons/base_tier_validation_formula/readme/USAGE.rst
odoo/addons/base_tier_validation_formula/static/description/icon.png
odoo/addons/base_tier_validation_formula/static/description/index.html
odoo/addons/base_tier_validation_formula/tests/__init__.py
odoo/addons/base_tier_validation_formula/tests/common.py
odoo/addons/base_tier_validation_formula/tests/test_tier_validation.py
odoo/addons/base_tier_validation_formula/tests/tier_validation_tester.py
odoo/addons/base_tier_validation_formula/views/tier_definition_view.xml
odoo12_addon_base_tier_validation_formula-12.0.2.0.1.dist-info/METADATA
odoo12_addon_base_tier_validation_formula-12.0.2.0.1.dist-info/WHEEL
odoo12_addon_base_tier_validation_formula-12.0.2.0.1.dist-info/top_level.txt
odoo12_addon_base_tier_validation_formula-12.0.2.0.1.dist-info/RECORD
