Metadata-Version: 2.1
Name: odoo12-addon-base-tier-validation-formula
Version: 12.0.2.0.1
Summary: Formulas for Base tier validation
Home-page: https://github.com/OCA/server-ux
Author: Creu Blanca,Odoo Community Association (OCA)
Author-email: support@odoo-community.org
License: AGPL-3
Platform: UNKNOWN
Classifier: Programming Language :: Python
Classifier: Framework :: Odoo
Classifier: License :: OSI Approved :: GNU Affero General Public License v3
Requires-Python: >=3.5
Requires-Dist: odoo12-addon-base-tier-validation
Requires-Dist: odoo (<12.1dev,>=12.0a)
